log_indented/__init__.py
log_indented/log_indented.py
log_indented/log_indented_test.py
log_indented-0.4.5.dist-info/LICENSE
log_indented-0.4.5.dist-info/METADATA
log_indented-0.4.5.dist-info/WHEEL
log_indented-0.4.5.dist-info/top_level.txt
log_indented-0.4.5.dist-info/RECORD
